rechunker/__init__.py
rechunker/_version.py
rechunker/algorithm.py
rechunker/api.py
rechunker/compat.py
rechunker/pipeline.py
rechunker/types.py
rechunker/executors/__init__.py
rechunker/executors/beam.py
rechunker/executors/dask.py
rechunker/executors/prefect.py
rechunker/executors/python.py
rechunker/executors/util.py
rechunker-0.5.4.dist-info/licenses/LICENSE
rechunker-0.5.4.dist-info/METADATA
rechunker-0.5.4.dist-info/WHEEL
rechunker-0.5.4.dist-info/top_level.txt
rechunker-0.5.4.dist-info/RECORD
