Metadata-Version: 2.4
Name: rechunker
Version: 0.5.4
Summary: A library for rechunking arrays
Author-email: Pangeo developers <ryan.abernathey@gmail.com>
License: MIT License
Project-URL: documentation, https://rechunker.readthedocs.io
Project-URL: homepage, https://pypi.org/project/rechunker/
Project-URL: repository, https://github.com/pangeo-data/rechunker
Requires-Python: >=3.8
License-File: LICENSE
Requires-Dist: dask[array,diagnostics]
Requires-Dist: mypy_extensions
Requires-Dist: packaging
Requires-Dist: zarr<3,>=2.11
Provides-Extra: complete
Requires-Dist: apache_beam>=2.28; extra == "complete"
Requires-Dist: fsspec; extra == "complete"
Requires-Dist: prefect<2; extra == "complete"
Requires-Dist: pyyaml; extra == "complete"
Requires-Dist: xarray>=2022.3; extra == "complete"
Provides-Extra: dev
Requires-Dist: black; extra == "dev"
Requires-Dist: codecov; extra == "dev"
Requires-Dist: flake8; extra == "dev"
Requires-Dist: hypothesis; extra == "dev"
Requires-Dist: IPython; extra == "dev"
Requires-Dist: mypy; extra == "dev"
Requires-Dist: nbsphinx; extra == "dev"
Requires-Dist: numpydoc; extra == "dev"
Requires-Dist: pytest; extra == "dev"
Requires-Dist: pytest-cov; extra == "dev"
Requires-Dist: sphinx; extra == "dev"
Requires-Dist: sphinx-pangeo-theme; extra == "dev"
Requires-Dist: sphinxcontrib-srclinks; extra == "dev"
Provides-Extra: docs
Requires-Dist: IPython; extra == "docs"
Requires-Dist: nbsphinx; extra == "docs"
Requires-Dist: numpydoc; extra == "docs"
Requires-Dist: sphinx; extra == "docs"
Requires-Dist: sphinx-pangeo-theme; extra == "docs"
Requires-Dist: sphinxcontrib-srclinks; extra == "docs"
Provides-Extra: test
Requires-Dist: hypothesis; extra == "test"
Requires-Dist: pytest; extra == "test"
Dynamic: license-file
